voxcov_py-0.2.8.dist-info/METADATA
voxcov_py-0.2.8.dist-info/WHEEL
voxcov/__init__.py
voxcov/voxcov.cpython-310-darwin.so
voxcov_py-0.2.8.dist-info/RECORD
