Metadata-Version: 2.1
Name: voxcov-py
Version: 0.2.8
Author: Thomas Mulvaney <mulvaney@mailbox.org>
Author-email: Thomas Mulvaney <mulvaney@mailbox.org>
